Metadata-Version: 1.0
Name: fbgg-distributions
Version: 0.1
Summary: Binomial and Gaussian distributions
Home-page: UNKNOWN
Author: Faizan Ahmed
Author-email: faizanahmed2395@gmail.com
License: UNKNOWN
Platform: UNKNOWN
